       1: ldc           #83                 // String Snowy
       3: putfield      #77                 // Field 
name:Ljava/lang/String;
       6: aload_0
       7: new           #68                 // class Name
      10: dup
      11: aload_0
      12: invokevirtual #85                 // Method 
name:()Ljava/lang/String;
      15: invokespecial #70                 // Method 
Name."<init>":(Ljava/lang/String;)V
      18: putfield      #80                 // Field any:Ljava/lang/Object;
      21: getstatic     #66                 // Field 
scala/Predef$.MODULE$:Lscala/Predef$;
      24: getstatic     #90                 // Field Name$.MODULE$:LName$;
      27: aload_0
      28: invokevirtual #85                 // Method 
name:()Ljava/lang/String;
      31: invokevirtual #94                 // Method 
Name$.length$extension:(Ljava/lang/String;)I
