// #output
       1: ldc           #78                 // String Snowy
       3: putfield      #75                 // Field 
name:Ljava/lang/String;
       6: getstatic     #64                 // Field 
scala/Predef$.MODULE$:Lscala/Predef$;
       9: getstatic     #83                 // Field Name$.MODULE$:LName$;
      12: aload_0
      13: invokevirtual #85                 // Method 
name:()Ljava/lang/String;
      16: invokevirtual #89                 // Method 
Name$.length$extension:(Ljava/lang/String;)I
      19: invokestatic  #95                 // Method 
scala/runtime/BoxesRunTime.boxToInteger:(I)Ljava/lang/Integer;
      22: invokevirtual #72                 // Method 
scala/Predef$.println:(Ljava/lang/Object;)V
      25: aload_0
      26: aload_0
      27: invokevirtual #85                 // Method 
name:()Ljava/lang/String;
      30: invokevirtual #97                 // Method 
printName:(Ljava/lang/String;)V
      33: return
// #output
