// #output
  private int mad(int);
    Code:
       0: iload_1
       1: iconst_0
       2: if_icmpne     15
       5: new           #14                 // class 
java/lang/RuntimeException
       8: dup
       9: ldc           #16                 // String Error
      11: invokespecial #20                 // Method 
java/lang/RuntimeException."<init>":(Ljava/lang/String;)V
      14: athrow
      15: iconst_1
      16: aload_0
      17: iload_1
      18: iconst_1
      19: isub
      20: invokespecial #22                 // Method mad:(I)I
      23: imul
      24: ireturn
// #output
