Compiled from "NoValVar.scala"
public class NoValVar {
  private final int number;
    descriptor: I

  public int getValue();
    descriptor: ()I
    Code:
       0: aload_0
       1: getfield      #14                 // Field number:I
       4: ireturn

  public NoValVar(int);
    descriptor: (I)V
    Code:
       0: aload_0
       1: iload_1
       2: putfield      #14                 // Field number:I
       5: aload_0
       6: invokespecial #21                 // Method 
java/lang/Object."<init>":()V
       9: return
}
