Compiled from "ScalaInt.scala"
public class ScalaInt extends java.lang.Object implements scala.ScalaObject{
public ScalaInt();
  Code:
   0:	aload_0
   1:	invokespecial	#10; //Method java/lang/Object."<init>":()V
   4:	return

public void playWithInt();
  Code:
   0:	ldc	#12; //int 10
   2:	istore_1
   3:	new	#14; //class java/util/ArrayList
   6:	dup
   7:	invokespecial	#15; //Method java/util/ArrayList."<init>":()V
   10:	astore_2
   11:	aload_2
   12:	iload_1
   13:	invokevirtual	#19; //Method java/util/ArrayList.ensureCapacity:(I)V
   16:	return

public int $tag()   throws java.rmi.RemoteException;
  Code:
   0:	aload_0
   1:	invokestatic	#33; //Method scala/ScalaObject$class.$tag:(Lscala/ScalaObject;)I
   4:	ireturn

}

